gpyocr/__init__.py
gpyocr/__main__.py
gpyocr/_gpyocr.py
tests/resources/__init__.py
gpyocr-1.4.dist-info/LICENSE
gpyocr-1.4.dist-info/METADATA
gpyocr-1.4.dist-info/WHEEL
gpyocr-1.4.dist-info/entry_points.txt
gpyocr-1.4.dist-info/top_level.txt
gpyocr-1.4.dist-info/RECORD
