Metadata-Version: 2.1
Name: gpyocr
Version: 1.4
Summary: Python wrapper for Tesseract OCR and Google Vision OCR
Home-page: https://github.com/ceccoemi/gpyocr
Author: Emilio Cecchini
Author-email: cecchini.mle@gmail.com
License: Apache 2.0
Keywords: OCR tesseract google vision wrapper
Platform: UNKNOWN
Classifier: Programming Language :: Python :: 3.6
Classifier: Programming Language :: Python :: 3.7
Classifier: License :: OSI Approved :: Apache Software License
Classifier: Topic :: Software Development :: Libraries :: Python Modules
Requires-Dist: opencv-python
Requires-Dist: Pillow
Requires-Dist: google-cloud-vision
